lightwave_smart/__init__.py
lightwave_smart/auth.py
lightwave_smart/device.py
lightwave_smart/lightwave_smart.py
lightwave_smart/link.py
lightwave_smart/message.py
lightwave_smart/products.py
lightwave_smart/utils.py
lightwave_smart/websocket.py
lightwave_smart-2.0.2.dist-info/licenses/LICENSE
lightwave_smart-2.0.2.dist-info/METADATA
lightwave_smart-2.0.2.dist-info/WHEEL
lightwave_smart-2.0.2.dist-info/top_level.txt
lightwave_smart-2.0.2.dist-info/RECORD
