Metadata-Version: 2.4
Name: lightwave_smart
Version: 2.0.2
Summary: Controls for Lightwave Smart Series (second generation) devices
Home-page: https://github.com/LightwaveSmartHome/lightwave_smart
Author: Bryan Blunt / Lightwave
Author-email: dev@lightwaverf.com
Classifier: Programming Language :: Python :: 3
Classifier: License :: OSI Approved :: MIT License
Classifier: Operating System :: OS Independent
License-File: LICENSE
Requires-Dist: aiohttp<=4
Dynamic: author
Dynamic: author-email
Dynamic: classifier
Dynamic: description
Dynamic: description-content-type
Dynamic: home-page
Dynamic: license-file
Dynamic: requires-dist
Dynamic: summary
